{"title":"네이버 공연 live beta ─ 전체일정","url":"https://live.naver.com/schedule","favicon":"https://live.naver.com/favicon.ico","elements":[{"title":"뮤지컬 <곤 투모로우> 전막 실황 생중계","contents":"01월 05일(수) 19:30","link":"https://tv.naver.com/l/95642","retrieved":1640919513004},{"title":"쇼핑\n\t\t\t\t\t\t\t\t\t\t뮤지컬 <곤 투모로우> 전막 실황 생중계 & 특별 할인","contents":"01월 05일(수) 19:30","link":"https://view.shoppinglive.naver.com/lives/373205","retrieved":1640919513005},{"title":"무용 <1687-움직임에 대한 원리> 녹화중계","contents":"01월 06일(목) 20:00","link":"https://tv.naver.com/l/92248","retrieved":1640091813393},{"title":"후원\n\t\t\t\t\t\t\t\t\t\t1/9 8PM 뮤지컬 <풍월주> 녹화중계 LIVE! | 2회차","contents":"01월 09일(일) 20:00","link":"https://tv.naver.com/l/93108","retrieved":1638220663831},{"title":"후원\n\t\t\t\t\t\t\t\t\t\t창작 뮤지컬 <브라더스 까라마조프>","contents":"01월 10일(월) 20:00","link":"https://tv.naver.com/l/92491","retrieved":1638220663832},{"title":"전통 <인당수의 우렁총각, 용궁출신입니다만>","contents":"01월 11일(화) 20:00","link":"https://tv.naver.com/l/92250","retrieved":1640091813398},{"title":"전통 <마음의 노래14> 녹화중계","contents":"01월 13일(목) 20:00","link":"https://tv.naver.com/l/92261","retrieved":1640091813398},{"title":"후원\n\t\t\t\t\t\t\t\t\t\t1/16 8PM 뮤지컬 <풍월주> 녹화중계 LIVE! | 3회차","contents":"01월 16일(일) 20:00","link":"https://tv.naver.com/l/93111","retrieved":1638220663833},{"title":"후원\n\t\t\t\t\t\t\t\t\t\t1/17 8PM 뮤지컬 <풍월주> 녹화중계 LIVE!","contents":"01월 17일(월) 20:00","link":"https://tv.naver.com/l/95885","retrieved":1641195647748},{"title":"연극 <친절한 에이미 선생님의 하루> 녹화중계","contents":"01월 18일(화) 20:00","link":"https://tv.naver.com/l/92742","retrieved":1640091813399},{"title":"무용 <3rd Altimeets> 녹화중계","contents":"01월 20일(목) 20:00","link":"https://tv.naver.com/l/93225","retrieved":1640091813400},{"title":"연극 <월드다방> 녹화중계","contents":"01월 25일(화) 20:00","link":"https://tv.naver.com/l/94276","retrieved":1640091813400},{"title":"연극 <서찰을 전하는 아이> 녹화중계","contents":"01월 27일(목) 20:00","link":"https://tv.naver.com/l/93433","retrieved":1640091813401}]}